literal_dict-1.1.0.dist-info/METADATA
literal_dict-1.1.0.dist-info/WHEEL
literal_dict.py
literal_dict-1.1.0.dist-info/RECORD
