Metadata-Version: 2.1
Name: literal-dict
Version: 1.1.0
Summary: Use JavaScript-like object definition syntax in Python
Author-Email: Muspi Merol <me@muspimerol.site>
License: MIT
Requires-Python: >=3.6
